bikipy/__init__.py
bikipy-0.1.0.dist-info/WHEEL
bikipy-0.1.0.dist-info/METADATA
bikipy-0.1.0.dist-info/RECORD
