Metadata-Version: 2.1
Name: bikipy
Version: 0.1.0
Summary: WiP
Author: Can H. Tartanoglu
Author-email: canhtart@gmail.com
Requires-Python: >=3.10,<4.0
Classifier: Programming Language :: Python :: 3
Classifier: Programming Language :: Python :: 3.10
